{"target": "Promate Electronic Co Ltd", "keywords": [{"KeyWords(Filtered)": [], "KeyWords(Emphasize)": ["connector"], "Keywords": ["electrical", "I/O", "board-to-board", "wire-to-board", "PCB"]}], "compLi_detail": [{"sic": "5045", "name": "ABC Data SA", "selected": false}, {"sic": "5063", "name": "Ace Pillar Co Ltd", "selected": false}, {"sic": "5065", "name": "Aerospace Communications Holdings Co Ltd", "selected": false}, {"sic": "5065", "name": "Alltek Technology Corp.", "selected": false}, {"sic": "5063", "name": "Anixter International Inc.", "selected": false}, {"sic": "5065", "name": "Answer Technology Co., Ltd.", "selected": false}, {"sic": "5045", "name": "Arena Bilgisayar Sanayi ve Ticaret AS", "selected": false}, {"sic": "5045", "name": "Armada Blgsyr Stmlr Sny ve Tcrt AS", "selected": false}, {"sic": "5065", "name": "Arrow Electronics, Inc.", "selected": false}, {"sic": "5045", "name": "ASBISc Enterprises Plc", "selected": false}, {"sic": "5065", "name": "ASEC International Corporation", "selected": false}, {"sic": "5065", "name": "Avnet, Inc.", "selected": false}, {"sic": "5065", "name": "BOS Better OnLine Sol (USA)", "selected": false}, {"sic": "5065", "name": "Chander Electronics Corp.", "selected": false}, {"sic": "5065", "name": "China Trends Holdings Limited", "selected": false}, {"sic": "5065", "name": "Daetwyler Holding AG", "selected": false}, {"sic": "5045", "name": "Daouincube Inc", "selected": false}, {"sic": "5065", "name": "Dragon Group International Limited", "selected": false}, {"sic": "5045", "name": "Dustin Group AB", "selected": false}, {"sic": "5065", "name": "EACO Corp", "selected": false}, {"sic": "5065", "name": "Eagle Mountain Corp", "selected": false}, {"sic": "5065", "name": "Edom Technology Co Ltd", "selected": false}, {"sic": "5063", "name": "Elematec Corporation", "selected": true}, {"sic": "5045", "name": "Esprinet SpA", "selected": false}, {"sic": "5065", "name": "Excel Co Ltd", "selected": true}, {"sic": "5045", "name": "FAST TECHNOLOGIES INC.", "selected": false}, {"sic": "5065", "name": "Fuhrmeister Electronics Co.,Ltd.", "selected": false}, {"sic": "5065", "name": "FUSO DENTSU CO., LTD.", "selected": false}, {"sic": "5045", "name": "GENESIS ENERGY SA", "selected": false}, {"sic": "5045", "name": "Genuine C&C Inc", "selected": false}, {"sic": "5045", "name": "GrandTech C.G. Systems Inc.", "selected": false}, {"sic": "5065", "name": "Gremz Inc", "selected": false}, {"sic": "5065", "name": "HAGIWARA ELECTRIC CO., LTD.", "selected": false}, {"sic": "5065", "name": "Hailiang International Holdings Ltd", "selected": false}, {"sic": "5065", "name": "Honey Hope Honesty Enterprise Co Ltd", "selected": false}, {"sic": "5063", "name": "Houston Wire & Cable Company", "selected": false}, {"sic": "5065", "name": "Howteh Technology Co., Ltd.", "selected": true}, {"sic": "5045", "name": "Hunan Copote Science & Tech Co., Ltd.", "selected": false}, {"sic": "5045", "name": "Ideiasnet SA", "selected": false}, {"sic": "5045", "name": "Indeks Bilgisayar Sistemleri Muhendislik", "selected": false}, {"sic": "5065", "name": "InfoSonics Corporation", "selected": false}, {"sic": "5045", "name": "Innovative Technology Development Corp", "selected": false}, {"sic": "5045", "name": "JC Hyun Systems Inc", "selected": false}, {"sic": "5045", "name": "Jiangsu Nandasoft Technology Co Ltd", "selected": false}, {"sic": "5065", "name": "KANADEN CORPORATION", "selected": false}, {"sic": "5045", "name": "Korea Information Engineering Services", "selected": false}, {"sic": "5065", "name": "Koryo Electronics Co Ltd", "selected": false}, {"sic": "5065", "name": "KUEN CHAANG UPPERTECH CORP.", "selected": false}, {"sic": "5065", "name": "KYOEI SANGYO CO., LTD.", "selected": false}, {"sic": "5065", "name": "Laird PLC", "selected": false}, {"sic": "5045", "name": "Leo Systems Inc", "selected": false}, {"sic": "5063", "name": "LG International Corp", "selected": false}, {"sic": "5065", "name": "LITE-ON JAPAN LTD.", "selected": false}, {"sic": "5045", "name": "Logicom Public Ltd", "selected": false}, {"sic": "5063", "name": "Malmbergs Elektriska AB", "selected": false}, {"sic": "5063", "name": "MANSEI CORPORATION", "selected": false}, {"sic": "5065", "name": "MARUBUN CORPORATION", "selected": false}, {"sic": "5065", "name": "MAXTEK TECHNOLOGY CO., LTD.", "selected": false}, {"sic": "5065", "name": "mDR Ltd", "selected": false}, {"sic": "5065", "name": "Merdeka Mobile Group Ltd", "selected": false}, {"sic": "5065", "name": "MetaTech (AP) Inc.", "selected": true}, {"sic": "5065", "name": "Naigai Tec Corporation", "selected": false}, {"sic": "5065", "name": "NICHIDENBO CORPORATION", "selected": false}, {"sic": "5065", "name": "NICHING INDUSTRIAL CORPORATION", "selected": false}, {"sic": "5065", "name": "NIPPO LTD.", "selected": false}, {"sic": "5063", "name": "OEM International AB", "selected": false}, {"sic": "5065", "name": "PALTEK CORPORATION", "selected": false}, {"sic": "5065", "name": "Perfect Optronics Ltd", "selected": false}, {"sic": "5065", "name": "Petrosetco Distribution Joint Stock Co", "selected": false}, {"sic": "5063", "name": "Pierides Holdings Plc", "selected": false}, {"sic": "5045", "name": "Pobis TNC Co Ltd", "selected": false}, {"sic": "5065", "name": "Podak Co Ltd", "selected": true}, {"sic": "5065", "name": "Premier Farnell plc", "selected": false}, {"sic": "5065", "name": "Professional Computer Technology Ltd", "selected": false}, {"sic": "5065", "name": "RADA Electronic Ind. Ltd.", "selected": false}, {"sic": "5065", "name": "Renesas Easton Co Ltd", "selected": false}, {"sic": "5065", "name": "Ryosan Company, Limited", "selected": false}, {"sic": "5065", "name": "Ryoyo Electro Corp", "selected": false}, {"sic": "5065", "name": "S.A.S. Dragon Holdings Limited", "selected": false}, {"sic": "5065", "name": "Sakae Electronics Corporation", "selected": true}, {"sic": "5065", "name": "Samart I-Mobile PCL", "selected": false}, {"sic": "5065", "name": "SANSHIN ELECTRONICS CO., LTD.", "selected": false}, {"sic": "5045", "name": "ScanSource, Inc.", "selected": false}, {"sic": "5063", "name": "SENSHU ELECTRIC CO., LTD.", "selected": false}, {"sic": "5065", "name": "Sentronic International Corp", "selected": false}, {"sic": "5065", "name": "Serial System Ltd", "selected": false}, {"sic": "5065", "name": "Shenzhen Aisidi Co., LTD.", "selected": false}, {"sic": "5065", "name": "Shenzhen Huakong Seg Co Ltd", "selected": false}, {"sic": "5065", "name": "Shinden Hightex Corp", "selected": false}, {"sic": "5065", "name": "Siltrontech Electronics Corporation", "selected": false}, {"sic": "5063", "name": "Solar A/S", "selected": false}, {"sic": "5063", "name": "Solomon Technology Corporation", "selected": false}, {"sic": "5065", "name": "Stokes Ltd", "selected": false}, {"sic": "5065", "name": "SUNNIC Technology & Merchandise Inc.", "selected": false}, {"sic": "5063", "name": "SUN-WA TECHNOS CORPORATION", "selected": false}, {"sic": "5065", "name": "Surge Components, Inc.", "selected": false}, {"sic": "5063", "name": "SUZUDEN CORPORATION", "selected": true}, {"sic": "5045", "name": "Synnex (Thailand) Public Company Limited", "selected": false}, {"sic": "5045", "name": "SYNNEX Corporation", "selected": false}, {"sic": "5045", "name": "Synnex Technology International Corp", "selected": false}, {"sic": "5065", "name": "Taitron Components Inc.", "selected": false}, {"sic": "5065", "name": "TAIWAN OSTOR CORP.", "selected": false}, {"sic": "5065", "name": "TAKACHIHO KOHEKI CO., LTD.", "selected": false}, {"sic": "5063", "name": "TANAKA CO., LTD.", "selected": true}, {"sic": "5065", "name": "TE Connectivity Ltd", "selected": false}, {"sic": "5045", "name": "Tech Data Corp", "selected": false}, {"sic": "5065", "name": "Techno Alpha Co., Ltd.", "selected": false}, {"sic": "5065", "name": "Tokai Electronics Co Ltd", "selected": false}, {"sic": "5065", "name": "Tokyo Electron Device Ltd", "selected": false}, {"sic": "5065", "name": "TOMEN DEVICES CORPORATION", "selected": false}, {"sic": "5065", "name": "Trust-Search Corp.,Ltd.", "selected": false}, {"sic": "5045", "name": "Unitech Computer Co Ltd", "selected": false}, {"sic": "5063", "name": "Vietnam Electric Cable Corp", "selected": false}, {"sic": "5065", "name": "VITEC CO., LTD.", "selected": true}, {"sic": "5065", "name": "V-Tac Technology Co., Ltd.", "selected": false}, {"sic": "5045", "name": "Weikeng Industrial Co. Ltd", "selected": false}, {"sic": "5065", "name": "WPG Holdings Limited", "selected": false}, {"sic": "5065", "name": "Wuhan P&S Information Technology Co Ltd", "selected": false}, {"sic": "5045", "name": "Xander International Corp.", "selected": true}, {"sic": "5063", "name": "Yleiselektroniikka Oyj", "selected": false}, {"sic": "5065", "name": "Zenitron Corp", "selected": false}, {"sic": "5045", "name": "Zero One Technology Co Ltd", "selected": false}, {"sic": "5045", "name": "Zheda Lande Scitech Limited", "selected": false}, {"sic": "5063", "name": "ZHONGYEDA ELECTRIC CO.,LTD.", "selected": false}], "compLi": ["ABC Data SA", "Ace Pillar Co Ltd", "Aerospace Communications Holdings Co Ltd", "Alltek Technology Corp.", "Anixter International Inc.", "Answer Technology Co., Ltd.", "Arena Bilgisayar Sanayi ve Ticaret AS", "Armada Blgsyr Stmlr Sny ve Tcrt AS", "Arrow Electronics, Inc.", "ASBISc Enterprises Plc", "ASEC International Corporation", "Avnet, Inc.", "BOS Better OnLine Sol (USA)", "Chander Electronics Corp.", "China Trends Holdings Limited", "Daetwyler Holding AG", "Daouincube Inc", "Dragon Group International Limited", "Dustin Group AB", "EACO Corp", "Eagle Mountain Corp", "Edom Technology Co Ltd", "Elematec Corporation", "Esprinet SpA", "Excel Co Ltd", "FAST TECHNOLOGIES INC.", "Fuhrmeister Electronics Co.,Ltd.", "FUSO DENTSU CO., LTD.", "GENESIS ENERGY SA", "Genuine C&C Inc", "GrandTech C.G. Systems Inc.", "Gremz Inc", "HAGIWARA ELECTRIC CO., LTD.", "Hailiang International Holdings Ltd", "Honey Hope Honesty Enterprise Co Ltd", "Houston Wire & Cable Company", "Howteh Technology Co., Ltd.", "Hunan Copote Science & Tech Co., Ltd.", "Ideiasnet SA", "Indeks Bilgisayar Sistemleri Muhendislik", "InfoSonics Corporation", "Innovative Technology Development Corp", "JC Hyun Systems Inc", "Jiangsu Nandasoft Technology Co Ltd", "KANADEN CORPORATION", "Korea Information Engineering Services", "Koryo Electronics Co Ltd", "KUEN CHAANG UPPERTECH CORP.", "KYOEI SANGYO CO., LTD.", "Laird PLC", "Leo Systems Inc", "LG International Corp", "LITE-ON JAPAN LTD.", "Logicom Public Ltd", "Malmbergs Elektriska AB", "MANSEI CORPORATION", "MARUBUN CORPORATION", "MAXTEK TECHNOLOGY CO., LTD.", "mDR Ltd", "Merdeka Mobile Group Ltd", "MetaTech (AP) Inc.", "Naigai Tec Corporation", "NICHIDENBO CORPORATION", "NICHING INDUSTRIAL CORPORATION", "NIPPO LTD.", "OEM International AB", "PALTEK CORPORATION", "Perfect Optronics Ltd", "Petrosetco Distribution Joint Stock Co", "Pierides Holdings Plc", "Pobis TNC Co Ltd", "Podak Co Ltd", "Premier Farnell plc", "Professional Computer Technology Ltd", "RADA Electronic Ind. Ltd.", "Renesas Easton Co Ltd", "Ryosan Company, Limited", "Ryoyo Electro Corp", "S.A.S. Dragon Holdings Limited", "Sakae Electronics Corporation", "Samart I-Mobile PCL", "SANSHIN ELECTRONICS CO., LTD.", "ScanSource, Inc.", "SENSHU ELECTRIC CO., LTD.", "Sentronic International Corp", "Serial System Ltd", "Shenzhen Aisidi Co., LTD.", "Shenzhen Huakong Seg Co Ltd", "Shinden Hightex Corp", "Siltrontech Electronics Corporation", "Solar A/S", "Solomon Technology Corporation", "Stokes Ltd", "SUNNIC Technology & Merchandise Inc.", "SUN-WA TECHNOS CORPORATION", "Surge Components, Inc.", "SUZUDEN CORPORATION", "Synnex (Thailand) Public Company Limited", "SYNNEX Corporation", "Synnex Technology International Corp", "Taitron Components Inc.", "TAIWAN OSTOR CORP.", "TAKACHIHO KOHEKI CO., LTD.", "TANAKA CO., LTD.", "TE Connectivity Ltd", "Tech Data Corp", "Techno Alpha Co., Ltd.", "Tokai Electronics Co Ltd", "Tokyo Electron Device Ltd", "TOMEN DEVICES CORPORATION", "Trust-Search Corp.,Ltd.", "Unitech Computer Co Ltd", "Vietnam Electric Cable Corp", "VITEC CO., LTD.", "V-Tac Technology Co., Ltd.", "Weikeng Industrial Co. Ltd", "WPG Holdings Limited", "Wuhan P&S Information Technology Co Ltd", "Xander International Corp.", "Yleiselektroniikka Oyj", "Zenitron Corp", "Zero One Technology Co Ltd", "Zheda Lande Scitech Limited", "ZHONGYEDA ELECTRIC CO.,LTD."], "website": "https://www.gtk.co.uk/"}